nas_mcp_server/__init__.py
nas_mcp_server/main.py
nas_mcp_server/bazarr/__init__.py
nas_mcp_server/bazarr/client.py
nas_mcp_server/bazarr/tools.py
nas_mcp_server/overseerr/__init__.py
nas_mcp_server/overseerr/client.py
nas_mcp_server/overseerr/tools.py
nas_mcp_server/plex/__init__.py
nas_mcp_server/plex/client.py
nas_mcp_server/plex/tools.py
nas_mcp_server/prowlarr/__init__.py
nas_mcp_server/prowlarr/client.py
nas_mcp_server/prowlarr/tools.py
nas_mcp_server/radarr/__init__.py
nas_mcp_server/radarr/client.py
nas_mcp_server/radarr/tools.py
nas_mcp_server/unified/__init__.py
nas_mcp_server/unified/tools.py
nas_mcp_server-0.0.3.dist-info/METADATA
nas_mcp_server-0.0.3.dist-info/WHEEL
nas_mcp_server-0.0.3.dist-info/entry_points.txt
nas_mcp_server-0.0.3.dist-info/RECORD
