Metadata-Version: 2.4
Name: nas-mcp-server
Version: 0.0.3
Summary: MCP server for Plex, Radarr, Overseerr, Bazarr, and Prowlarr
Project-URL: Homepage, https://github.com/matthieurosset/nas-mcp-server
Project-URL: Repository, https://github.com/matthieurosset/nas-mcp-server
Author: Matthieu Rosset
License-Expression: MIT
Keywords: bazarr,mcp,media,nas,overseerr,plex,prowlarr,radarr,subtitles
Classifier: Development Status :: 4 - Beta
Classifier: Intended Audience :: End Users/Desktop
Classifier: License :: OSI Approved :: MIT License
Classifier: Programming Language :: Python :: 3
Classifier: Programming Language :: Python :: 3.10
Classifier: Programming Language :: Python :: 3.11
Classifier: Programming Language :: Python :: 3.12
Requires-Python: >=3.10
Requires-Dist: fastmcp>=2.0.0
Requires-Dist: httpx>=0.27.0
Requires-Dist: python-dotenv>=1.0.0
